awsfind/__init__.py
awsfind/find.py
awsfind-0.4.0.dist-info/entry_points.txt
awsfind-0.4.0.dist-info/WHEEL
awsfind-0.4.0.dist-info/METADATA
awsfind-0.4.0.dist-info/RECORD
