Metadata-Version: 2.1
Name: awsfind
Version: 0.4.0
Summary: searches across all accounts and regions known to chaim for the item(s)
Author: ccdale
Author-email: chris.allison@hivehome.com
Requires-Python: >=3.6,<4.0
Classifier: Programming Language :: Python :: 3
Classifier: Programming Language :: Python :: 3.6
Classifier: Programming Language :: Python :: 3.7
Classifier: Programming Language :: Python :: 3.8
Requires-Dist: boto3 (>=1.11.9,<2.0.0)
Requires-Dist: ccaaws (>=0.4.6,<0.5.0)
Requires-Dist: ccalogging (>=0.3.3,<0.4.0)
Requires-Dist: ccautils (>=0.4.2,<0.5.0)
Requires-Dist: chaim (>=0.8.0,<0.9.0)
Requires-Dist: toml (>=0.10.0,<0.11.0)
